{"cameraMode":{"drawMode":0,"name":"Shaded","section":"Shading Mode"},"sceneLighting":true,"audioPlay":false,"sceneViewState":{"m_AlwaysRefresh":false,"showFog":true,"showSkybox":true,"showFlares":true,"showImageEffects":true,"showParticleSystems":true,"showVisualEffectGraphs":true,"m_FxEnabled":true},"in2DMode":false,"pivot":{"x":-0.4942520558834076,"y":5.050055027008057,"z":-5.247494220733643},"rotation":{"x":0.133783221244812,"y":0.05497196316719055,"z":-0.007422807160764933,"w":0.9894123077392578},"size":1.7036725282669068,"orthographic":false}